LICENSE
README.md
setup.py
django_multitenant/__init__.py
django_multitenant/apps.py
django_multitenant/deletion.py
django_multitenant/django_mt_environment.py
django_multitenant/django_multitenant.py
django_multitenant/exceptions.py
django_multitenant/fields.py
django_multitenant/middlewares.py
django_multitenant/mixins.py
django_multitenant/models.py
django_multitenant/query.py
django_multitenant/settings.py
django_multitenant/utils.py
django_multitenant/views.py
django_multitenant/backends/__init__.py
django_multitenant/backends/postgresql/__init__.py
django_multitenant/backends/postgresql/base.py
django_multitenant/db/__init__.py
django_multitenant/db/migrations/__init__.py
django_multitenant/db/migrations/distribute.py
gindix_multitenant.egg-info/PKG-INFO
gindix_multitenant.egg-info/SOURCES.txt
gindix_multitenant.egg-info/dependency_links.txt
gindix_multitenant.egg-info/top_level.txt