Metadata-Version: 2.1
Name: gindix-multitenant
Version: 3.1.1
Summary: Django Library to Implement Multi-tenant databases
Home-page: https://github.com/citusdata/django-multitenant
Author: Louise Grandjonc
Author-email: louise.grandjonc@microsoft.com
Keywords: citus django multi tenantdjango postgres multi-tenant
Classifier: Development Status :: 5 - Production/Stable 
Classifier: Topic :: Database
Classifier: License :: OSI Approved :: MIT License
Classifier: Intended Audience :: Developers
Classifier: Programming Language :: Python :: 3
Classifier: Programming Language :: Python :: 3 :: Only
Classifier: Programming Language :: Python :: 3.7
Classifier: Programming Language :: Python :: 3.8
Classifier: Programming Language :: Python :: 3.9
Classifier: Programming Language :: Python :: 3.10
Classifier: Programming Language :: Python :: 3.11
License-File: LICENSE
